LICENSE
neuralsens/__init__.py
neuralsens/activation_functions.py
neuralsens/daily_demand_tr.py
neuralsens/data/daily_demand_tr.csv
neuralsens/data/daily_demand_tv.csv
neuralsens/interaction_invariant.py
neuralsens/meta.yaml
neuralsens/partial_derivatives.py
neuralsens/significance_test.py
neuralsens-0.0.26.dist-info/LICENSE
neuralsens-0.0.26.dist-info/METADATA
neuralsens-0.0.26.dist-info/WHEEL
neuralsens-0.0.26.dist-info/RECORD
