Metadata-Version: 2.1
Name: neuralsens
Version: 0.0.26
Summary: The neuralsens package facilitates sensitivity analysis on neural network models, quantifying input importance. It provides functions for calculating and plotting input significance, and obtaining neuron layer activation functions and derivatives. Compatible with models created in R and Python, it's a robust toolkit for understanding input contributions in neural networks.
Home-page: https://github.com/JaiPizGon/NeuralSens
License: GPU-3
Author: Jaime Pizarroso Gonzalo
Requires-Python: >=3.8
Classifier: License :: Other/Proprietary License
Classifier: Programming Language :: Python :: 3
Classifier: Programming Language :: Python :: 3.8
Classifier: Programming Language :: Python :: 3.9
Classifier: Programming Language :: Python :: 3.10
Classifier: Programming Language :: Python :: 3.11
Classifier: Programming Language :: Python :: 3.12
Requires-Dist: adjustText (>=0.8,<0.9)
Requires-Dist: matplotlib (>=3.5.2)
Requires-Dist: numpy (>=1.22.4)
Requires-Dist: pandas (>=2.0.0)
Requires-Dist: plotly (>=5.11.0)
Requires-Dist: scipy (>=1.8.1)
Project-URL: Repository, https://github.com/JaiPizGon/NeuralSens/python
